MANIFEST.in
README.md
requirements.txt
setup.py
python_dxh/__init__.py
python_dxh/__version__.py
python_dxh/decorator.py
python_dxh/main.py
python_dxh/middleware.py
python_dxh/obj_converter.py
python_dxh/response.py
python_dxh/utilities.py
python_dxh/validators.py
python_dxh.egg-info/PKG-INFO
python_dxh.egg-info/SOURCES.txt
python_dxh.egg-info/dependency_links.txt
python_dxh.egg-info/requires.txt
python_dxh.egg-info/top_level.txt
python_dxh/anticaptcha/__init__.py
python_dxh/anticaptcha/captcha.py
python_dxh/aws/__init__.py
python_dxh/aws/s3_client.py
python_dxh/aws/textract.py
python_dxh/config/__init__.py
python_dxh/config/settings.py