Metadata-Version: 2.1
Name: python-dxh
Version: 1.2.2
Summary: A Python package for developments.
Home-page: https://github.com/git-foysal-1/python-dxh.git
Author: DevXhub
License: MIT
Project-URL: Source, https://github.com/git-foysal-1/python-dxh.git
Keywords: python,object
Platform: UNKNOWN
Classifier: Development Status :: 4 - Beta
Classifier: Intended Audience :: Developers
Classifier: License :: OSI Approved :: BSD License
Classifier: Natural Language :: English
Classifier: Operating System :: OS Independent
Classifier: Programming Language :: Python
Classifier: Programming Language :: Python :: 3
Classifier: Programming Language :: Python :: 3.11
Classifier: Programming Language :: Python :: Implementation :: CPython
Classifier: Topic :: Software Development
Classifier: Topic :: Software Development :: Libraries :: Python Modules
Requires-Python: >=3.9
